<instance>
  <presentation name="instance24" type="DCOP" benchmark="RandomDCOP" model="Simple" constraintModel="TKC" format="XDisCSP 1.0" />
  <agents nbAgents="18">
    <agent name="A1" id="1" description="Agent 1" />
    <agent name="A2" id="2" description="Agent 2" />
    <agent name="A3" id="3" description="Agent 3" />
    <agent name="A4" id="4" description="Agent 4" />
    <agent name="A5" id="5" description="Agent 5" />
    <agent name="A6" id="6" description="Agent 6" />
    <agent name="A7" id="7" description="Agent 7" />
    <agent name="A8" id="8" description="Agent 8" />
    <agent name="A9" id="9" description="Agent 9" />
    <agent name="A10" id="10" description="Agent 10" />
    <agent name="A11" id="11" description="Agent 11" />
    <agent name="A12" id="12" description="Agent 12" />
    <agent name="A13" id="13" description="Agent 13" />
    <agent name="A14" id="14" description="Agent 14" />
    <agent name="A15" id="15" description="Agent 15" />
    <agent name="A16" id="16" description="Agent 16" />
    <agent name="A17" id="17" description="Agent 17" />
    <agent name="A18" id="18" description="Agent 18" />
  </agents>
  <domains nbDomains="1">
    <domain name="D1" nbValues="7">1..7</domain>
  </domains>
  <variables nbVariables="18">
    <variable agent="A1" name="X1.1" id="1" domain="D1" description="variable 1.1" />
    <variable agent="A2" name="X2.1" id="1" domain="D1" description="variable 2.1" />
    <variable agent="A3" name="X3.1" id="1" domain="D1" description="variable 3.1" />
    <variable agent="A4" name="X4.1" id="1" domain="D1" description="variable 4.1" />
    <variable agent="A5" name="X5.1" id="1" domain="D1" description="variable 5.1" />
    <variable agent="A6" name="X6.1" id="1" domain="D1" description="variable 6.1" />
    <variable agent="A7" name="X7.1" id="1" domain="D1" description="variable 7.1" />
    <variable agent="A8" name="X8.1" id="1" domain="D1" description="variable 8.1" />
    <variable agent="A9" name="X9.1" id="1" domain="D1" description="variable 9.1" />
    <variable agent="A10" name="X10.1" id="1" domain="D1" description="variable 10.1" />
    <variable agent="A11" name="X11.1" id="1" domain="D1" description="variable 11.1" />
    <variable agent="A12" name="X12.1" id="1" domain="D1" description="variable 12.1" />
    <variable agent="A13" name="X13.1" id="1" domain="D1" description="variable 13.1" />
    <variable agent="A14" name="X14.1" id="1" domain="D1" description="variable 14.1" />
    <variable agent="A15" name="X15.1" id="1" domain="D1" description="variable 15.1" />
    <variable agent="A16" name="X16.1" id="1" domain="D1" description="variable 16.1" />
    <variable agent="A17" name="X17.1" id="1" domain="D1" description="variable 17.1" />
    <variable agent="A18" name="X18.1" id="1" domain="D1" description="variable 18.1" />
  </variables>
  <constraints nbConstraints="30">
    <constraint name="C0" model="TKC" arity="2" scope="X5.1 X10.1" reference="R0" />
    <constraint name="C1" model="TKC" arity="2" scope="X7.1 X18.1" reference="R1" />
    <constraint name="C2" model="TKC" arity="2" scope="X1.1 X14.1" reference="R2" />
    <constraint name="C3" model="TKC" arity="2" scope="X8.1 X16.1" reference="R3" />
    <constraint name="C4" model="TKC" arity="2" scope="X11.1 X15.1" reference="R4" />
    <constraint name="C5" model="TKC" arity="2" scope="X14.1 X16.1" reference="R5" />
    <constraint name="C6" model="TKC" arity="2" scope="X9.1 X14.1" reference="R6" />
    <constraint name="C7" model="TKC" arity="2" scope="X5.1 X16.1" reference="R7" />
    <constraint name="C8" model="TKC" arity="2" scope="X1.1 X15.1" reference="R8" />
    <constraint name="C9" model="TKC" arity="2" scope="X3.1 X5.1" reference="R9" />
    <constraint name="C10" model="TKC" arity="2" scope="X1.1 X6.1" reference="R10" />
    <constraint name="C11" model="TKC" arity="2" scope="X12.1 X15.1" reference="R11" />
    <constraint name="C12" model="TKC" arity="2" scope="X10.1 X18.1" reference="R12" />
    <constraint name="C13" model="TKC" arity="2" scope="X2.1 X10.1" reference="R13" />
    <constraint name="C14" model="TKC" arity="2" scope="X5.1 X13.1" reference="R14" />
    <constraint name="C15" model="TKC" arity="2" scope="X4.1 X15.1" reference="R15" />
    <constraint name="C16" model="TKC" arity="2" scope="X4.1 X17.1" reference="R16" />
    <constraint name="C17" model="TKC" arity="2" scope="X6.1 X7.1" reference="R17" />
    <constraint name="C18" model="TKC" arity="2" scope="X2.1 X13.1" reference="R18" />
    <constraint name="C19" model="TKC" arity="2" scope="X15.1 X16.1" reference="R19" />
    <constraint name="C20" model="TKC" arity="2" scope="X4.1 X8.1" reference="R20" />
    <constraint name="C21" model="TKC" arity="2" scope="X12.1 X17.1" reference="R21" />
    <constraint name="C22" model="TKC" arity="2" scope="X16.1 X18.1" reference="R22" />
    <constraint name="C23" model="TKC" arity="2" scope="X3.1 X4.1" reference="R23" />
    <constraint name="C24" model="TKC" arity="2" scope="X14.1 X18.1" reference="R24" />
    <constraint name="C25" model="TKC" arity="2" scope="X12.1 X16.1" reference="R25" />
    <constraint name="C26" model="TKC" arity="2" scope="X1.1 X18.1" reference="R26" />
    <constraint name="C27" model="TKC" arity="2" scope="X7.1 X16.1" reference="R27" />
    <constraint name="C28" model="TKC" arity="2" scope="X15.1 X18.1" reference="R28" />
    <constraint name="C29" model="TKC" arity="2" scope="X4.1 X18.1" reference="R29" />
  </constraints>
  <relations nbRelations="30">
    <relation name="R0" arity="2" nbTuples="49" semantics="soft" defaultCost="infinity">29:1 1|68:1 2|18:1 3|79:1 4|72:1 5|67:1 6|40:1 7|26:2 1|97:2 2|41:2 3|6:2 4|84:2 5|61:2 6|18:2 7|66:3 1|37:3 2|22:3 3|1:3 4|46:3 5|8:3 6|36:3 7|95:4 1|23:4 2|57:4 3|100:4 4|74:4 5|13:4 6|5:4 7|23:5 1|12:5 2|28:5 3|67:5 4|49:5 5|76:5 6|27:5 7|69:6 1|43:6 2|49:6 3|70:6 4|86:6 5|41:6 6|81:6 7|1:7 1|91:7 2|48:7 3|63:7 4|29:7 5|73:7 6|24:7 7</relation>
    <relation name="R1" arity="2" nbTuples="49" semantics="soft" defaultCost="infinity">37:1 1|91:1 2|34:1 3|47:1 4|96:1 5|94:1 6|86:1 7|59:2 1|1:2 2|15:2 3|75:2 4|92:2 5|48:2 6|96:2 7|22:3 1|57:3 2|19:3 3|94:3 4|64:3 5|96:3 6|63:3 7|9:4 1|32:4 2|0:4 3|64:4 4|39:4 5|25:4 6|7:4 7|45:5 1|59:5 2|13:5 3|84:5 4|14:5 5|87:5 6|72:5 7|47:6 1|13:6 2|43:6 3|2:6 4|79:6 5|46:6 6|57:6 7|13:7 1|90:7 2|59:7 3|68:7 4|31:7 5|56:7 6|42:7 7</relation>
    <relation name="R2" arity="2" nbTuples="49" semantics="soft" defaultCost="infinity">80:1 1|3:1 2|45:1 3|45:1 4|51:1 5|9:1 6|86:1 7|72:2 1|29:2 2|15:2 3|84:2 4|99:2 5|31:2 6|57:2 7|3:3 1|81:3 2|45:3 3|81:3 4|88:3 5|50:3 6|0:3 7|99:4 1|27:4 2|89:4 3|44:4 4|6:4 5|36:4 6|41:4 7|46:5 1|81:5 2|45:5 3|1:5 4|32:5 5|59:5 6|62:5 7|100:6 1|58:6 2|87:6 3|24:6 4|71:6 5|96:6 6|92:6 7|19:7 1|45:7 2|58:7 3|62:7 4|96:7 5|63:7 6|15:7 7</relation>
    <relation name="R3" arity="2" nbTuples="49" semantics="soft" defaultCost="infinity">43:1 1|74:1 2|94:1 3|36:1 4|61:1 5|30:1 6|17:1 7|28:2 1|29:2 2|83:2 3|54:2 4|12:2 5|91:2 6|2:2 7|11:3 1|48:3 2|23:3 3|35:3 4|40:3 5|56:3 6|9:3 7|8:4 1|65:4 2|2:4 3|83:4 4|83:4 5|49:4 6|33:4 7|99:5 1|84:5 2|34:5 3|60:5 4|66:5 5|51:5 6|84:5 7|61:6 1|28:6 2|35:6 3|98:6 4|41:6 5|65:6 6|46:6 7|91:7 1|91:7 2|72:7 3|100:7 4|23:7 5|56:7 6|22:7 7</relation>
    <relation name="R4" arity="2" nbTuples="49" semantics="soft" defaultCost="infinity">66:1 1|75:1 2|49:1 3|53:1 4|61:1 5|76:1 6|92:1 7|27:2 1|5:2 2|3:2 3|5:2 4|15:2 5|21:2 6|96:2 7|56:3 1|1:3 2|5:3 3|94:3 4|57:3 5|65:3 6|91:3 7|59:4 1|56:4 2|23:4 3|70:4 4|67:4 5|32:4 6|12:4 7|37:5 1|17:5 2|39:5 3|49:5 4|81:5 5|1:5 6|62:5 7|21:6 1|31:6 2|48:6 3|58:6 4|23:6 5|65:6 6|31:6 7|82:7 1|40:7 2|50:7 3|87:7 4|26:7 5|100:7 6|91:7 7</relation>
    <relation name="R5" arity="2" nbTuples="49" semantics="soft" defaultCost="infinity">53:1 1|36:1 2|66:1 3|50:1 4|16:1 5|65:1 6|6:1 7|10:2 1|47:2 2|26:2 3|83:2 4|13:2 5|25:2 6|70:2 7|29:3 1|75:3 2|37:3 3|11:3 4|57:3 5|10:3 6|74:3 7|45:4 1|96:4 2|72:4 3|23:4 4|43:4 5|96:4 6|67:4 7|21:5 1|85:5 2|83:5 3|81:5 4|79:5 5|14:5 6|83:5 7|6:6 1|7:6 2|91:6 3|83:6 4|42:6 5|88:6 6|37:6 7|71:7 1|3:7 2|84:7 3|75:7 4|4:7 5|74:7 6|66:7 7</relation>
    <relation name="R6" arity="2" nbTuples="49" semantics="soft" defaultCost="infinity">93:1 1|85:1 2|81:1 3|54:1 4|65:1 5|85:1 6|99:1 7|92:2 1|2:2 2|50:2 3|32:2 4|50:2 5|16:2 6|40:2 7|53:3 1|40:3 2|21:3 3|77:3 4|47:3 5|60:3 6|19:3 7|95:4 1|95:4 2|3:4 3|65:4 4|43:4 5|79:4 6|1:4 7|24:5 1|45:5 2|28:5 3|15:5 4|0:5 5|72:5 6|81:5 7|69:6 1|39:6 2|67:6 3|23:6 4|52:6 5|68:6 6|89:6 7|87:7 1|38:7 2|79:7 3|59:7 4|87:7 5|51:7 6|27:7 7</relation>
    <relation name="R7" arity="2" nbTuples="49" semantics="soft" defaultCost="infinity">97:1 1|33:1 2|88:1 3|55:1 4|90:1 5|13:1 6|63:1 7|30:2 1|24:2 2|42:2 3|58:2 4|44:2 5|91:2 6|28:2 7|60:3 1|69:3 2|22:3 3|99:3 4|90:3 5|77:3 6|100:3 7|2:4 1|34:4 2|51:4 3|3:4 4|7:4 5|87:4 6|29:4 7|69:5 1|93:5 2|76:5 3|100:5 4|79:5 5|10:5 6|99:5 7|6:6 1|77:6 2|40:6 3|12:6 4|88:6 5|9:6 6|88:6 7|28:7 1|59:7 2|5:7 3|44:7 4|44:7 5|42:7 6|89:7 7</relation>
    <relation name="R8" arity="2" nbTuples="49" semantics="soft" defaultCost="infinity">93:1 1|1:1 2|65:1 3|87:1 4|68:1 5|10:1 6|83:1 7|24:2 1|83:2 2|58:2 3|75:2 4|17:2 5|65:2 6|77:2 7|80:3 1|78:3 2|36:3 3|45:3 4|96:3 5|2:3 6|27:3 7|16:4 1|59:4 2|96:4 3|93:4 4|30:4 5|53:4 6|70:4 7|91:5 1|34:5 2|64:5 3|14:5 4|35:5 5|63:5 6|90:5 7|72:6 1|49:6 2|54:6 3|66:6 4|56:6 5|6:6 6|41:6 7|51:7 1|72:7 2|62:7 3|69:7 4|93:7 5|18:7 6|40:7 7</relation>
    <relation name="R9" arity="2" nbTuples="49" semantics="soft" defaultCost="infinity">85:1 1|85:1 2|63:1 3|68:1 4|27:1 5|97:1 6|40:1 7|30:2 1|97:2 2|63:2 3|92:2 4|20:2 5|94:2 6|95:2 7|100:3 1|81:3 2|79:3 3|82:3 4|59:3 5|19:3 6|20:3 7|49:4 1|55:4 2|11:4 3|37:4 4|19:4 5|37:4 6|9:4 7|14:5 1|72:5 2|70:5 3|0:5 4|73:5 5|40:5 6|30:5 7|59:6 1|82:6 2|68:6 3|47:6 4|1:6 5|71:6 6|86:6 7|41:7 1|37:7 2|86:7 3|54:7 4|85:7 5|60:7 6|10:7 7</relation>
    <relation name="R10" arity="2" nbTuples="49" semantics="soft" defaultCost="infinity">89:1 1|52:1 2|69:1 3|58:1 4|21:1 5|24:1 6|12:1 7|65:2 1|0:2 2|14:2 3|27:2 4|34:2 5|15:2 6|52:2 7|55:3 1|82:3 2|13:3 3|6:3 4|83:3 5|19:3 6|67:3 7|74:4 1|5:4 2|35:4 3|24:4 4|13:4 5|38:4 6|99:4 7|93:5 1|74:5 2|99:5 3|100:5 4|68:5 5|25:5 6|0:5 7|34:6 1|42:6 2|33:6 3|85:6 4|2:6 5|20:6 6|67:6 7|80:7 1|44:7 2|71:7 3|60:7 4|27:7 5|39:7 6|49:7 7</relation>
    <relation name="R11" arity="2" nbTuples="49" semantics="soft" defaultCost="infinity">11:1 1|18:1 2|28:1 3|52:1 4|63:1 5|20:1 6|52:1 7|48:2 1|17:2 2|80:2 3|93:2 4|77:2 5|69:2 6|62:2 7|26:3 1|7:3 2|14:3 3|52:3 4|99:3 5|84:3 6|66:3 7|66:4 1|44:4 2|90:4 3|24:4 4|61:4 5|21:4 6|31:4 7|20:5 1|91:5 2|95:5 3|15:5 4|79:5 5|76:5 6|12:5 7|4:6 1|6:6 2|19:6 3|41:6 4|84:6 5|84:6 6|67:6 7|83:7 1|10:7 2|37:7 3|21:7 4|85:7 5|73:7 6|38:7 7</relation>
    <relation name="R12" arity="2" nbTuples="49" semantics="soft" defaultCost="infinity">46:1 1|60:1 2|5:1 3|89:1 4|75:1 5|84:1 6|3:1 7|5:2 1|92:2 2|93:2 3|70:2 4|63:2 5|41:2 6|14:2 7|67:3 1|95:3 2|54:3 3|91:3 4|15:3 5|23:3 6|9:3 7|77:4 1|29:4 2|5:4 3|69:4 4|35:4 5|77:4 6|0:4 7|52:5 1|91:5 2|76:5 3|36:5 4|55:5 5|100:5 6|58:5 7|52:6 1|69:6 2|30:6 3|71:6 4|65:6 5|52:6 6|44:6 7|98:7 1|29:7 2|10:7 3|95:7 4|23:7 5|47:7 6|27:7 7</relation>
    <relation name="R13" arity="2" nbTuples="49" semantics="soft" defaultCost="infinity">9:1 1|95:1 2|73:1 3|90:1 4|8:1 5|90:1 6|97:1 7|63:2 1|94:2 2|5:2 3|49:2 4|47:2 5|5:2 6|71:2 7|44:3 1|5:3 2|95:3 3|99:3 4|7:3 5|14:3 6|37:3 7|63:4 1|75:4 2|31:4 3|65:4 4|37:4 5|96:4 6|92:4 7|2:5 1|78:5 2|12:5 3|53:5 4|96:5 5|13:5 6|84:5 7|44:6 1|10:6 2|48:6 3|83:6 4|97:6 5|30:6 6|66:6 7|84:7 1|67:7 2|97:7 3|77:7 4|78:7 5|98:7 6|84:7 7</relation>
    <relation name="R14" arity="2" nbTuples="49" semantics="soft" defaultCost="infinity">47:1 1|54:1 2|88:1 3|66:1 4|94:1 5|16:1 6|7:1 7|6:2 1|30:2 2|27:2 3|0:2 4|47:2 5|33:2 6|56:2 7|8:3 1|18:3 2|57:3 3|19:3 4|49:3 5|55:3 6|48:3 7|8:4 1|79:4 2|23:4 3|80:4 4|80:4 5|2:4 6|10:4 7|17:5 1|58:5 2|49:5 3|45:5 4|55:5 5|9:5 6|2:5 7|74:6 1|16:6 2|7:6 3|50:6 4|71:6 5|69:6 6|57:6 7|55:7 1|66:7 2|56:7 3|66:7 4|49:7 5|91:7 6|15:7 7</relation>
    <relation name="R15" arity="2" nbTuples="49" semantics="soft" defaultCost="infinity">55:1 1|14:1 2|6:1 3|12:1 4|77:1 5|99:1 6|55:1 7|71:2 1|77:2 2|74:2 3|80:2 4|99:2 5|54:2 6|71:2 7|3:3 1|4:3 2|10:3 3|55:3 4|16:3 5|56:3 6|51:3 7|51:4 1|29:4 2|47:4 3|84:4 4|81:4 5|45:4 6|62:4 7|4:5 1|91:5 2|84:5 3|97:5 4|89:5 5|46:5 6|49:5 7|78:6 1|11:6 2|61:6 3|41:6 4|25:6 5|93:6 6|45:6 7|53:7 1|98:7 2|46:7 3|64:7 4|64:7 5|33:7 6|28:7 7</relation>
    <relation name="R16" arity="2" nbTuples="49" semantics="soft" defaultCost="infinity">5:1 1|91:1 2|57:1 3|13:1 4|74:1 5|53:1 6|43:1 7|5:2 1|41:2 2|56:2 3|22:2 4|94:2 5|22:2 6|75:2 7|56:3 1|78:3 2|31:3 3|33:3 4|66:3 5|41:3 6|58:3 7|78:4 1|91:4 2|64:4 3|71:4 4|46:4 5|87:4 6|21:4 7|40:5 1|66:5 2|82:5 3|17:5 4|74:5 5|93:5 6|60:5 7|15:6 1|34:6 2|83:6 3|24:6 4|67:6 5|100:6 6|29:6 7|98:7 1|19:7 2|39:7 3|13:7 4|62:7 5|93:7 6|53:7 7</relation>
    <relation name="R17" arity="2" nbTuples="49" semantics="soft" defaultCost="infinity">43:1 1|64:1 2|15:1 3|56:1 4|20:1 5|85:1 6|15:1 7|65:2 1|23:2 2|79:2 3|96:2 4|67:2 5|71:2 6|70:2 7|88:3 1|64:3 2|99:3 3|4:3 4|66:3 5|1:3 6|14:3 7|75:4 1|38:4 2|95:4 3|39:4 4|95:4 5|60:4 6|2:4 7|20:5 1|82:5 2|4:5 3|26:5 4|3:5 5|45:5 6|37:5 7|10:6 1|83:6 2|46:6 3|40:6 4|93:6 5|99:6 6|98:6 7|50:7 1|44:7 2|63:7 3|90:7 4|97:7 5|19:7 6|83:7 7</relation>
    <relation name="R18" arity="2" nbTuples="49" semantics="soft" defaultCost="infinity">59:1 1|4:1 2|30:1 3|12:1 4|51:1 5|20:1 6|46:1 7|24:2 1|51:2 2|43:2 3|23:2 4|3:2 5|93:2 6|93:2 7|63:3 1|96:3 2|7:3 3|26:3 4|11:3 5|66:3 6|98:3 7|24:4 1|91:4 2|69:4 3|71:4 4|3:4 5|98:4 6|86:4 7|34:5 1|78:5 2|91:5 3|47:5 4|65:5 5|79:5 6|10:5 7|48:6 1|65:6 2|67:6 3|94:6 4|26:6 5|42:6 6|25:6 7|73:7 1|7:7 2|14:7 3|76:7 4|58:7 5|6:7 6|34:7 7</relation>
    <relation name="R19" arity="2" nbTuples="49" semantics="soft" defaultCost="infinity">7:1 1|44:1 2|3:1 3|37:1 4|82:1 5|10:1 6|66:1 7|53:2 1|3:2 2|2:2 3|98:2 4|44:2 5|79:2 6|44:2 7|82:3 1|19:3 2|42:3 3|47:3 4|66:3 5|83:3 6|43:3 7|46:4 1|60:4 2|12:4 3|0:4 4|17:4 5|75:4 6|76:4 7|77:5 1|100:5 2|1:5 3|85:5 4|20:5 5|83:5 6|43:5 7|58:6 1|20:6 2|89:6 3|33:6 4|71:6 5|45:6 6|30:6 7|54:7 1|80:7 2|39:7 3|78:7 4|54:7 5|74:7 6|80:7 7</relation>
    <relation name="R20" arity="2" nbTuples="49" semantics="soft" defaultCost="infinity">61:1 1|65:1 2|59:1 3|99:1 4|63:1 5|0:1 6|36:1 7|27:2 1|76:2 2|48:2 3|96:2 4|99:2 5|12:2 6|26:2 7|12:3 1|58:3 2|4:3 3|46:3 4|91:3 5|32:3 6|39:3 7|33:4 1|93:4 2|16:4 3|19:4 4|14:4 5|23:4 6|81:4 7|80:5 1|14:5 2|65:5 3|58:5 4|21:5 5|22:5 6|90:5 7|70:6 1|67:6 2|4:6 3|0:6 4|86:6 5|4:6 6|90:6 7|98:7 1|39:7 2|13:7 3|23:7 4|96:7 5|27:7 6|31:7 7</relation>
    <relation name="R21" arity="2" nbTuples="49" semantics="soft" defaultCost="infinity">8:1 1|67:1 2|7:1 3|71:1 4|74:1 5|22:1 6|60:1 7|72:2 1|76:2 2|99:2 3|34:2 4|98:2 5|35:2 6|60:2 7|96:3 1|95:3 2|20:3 3|95:3 4|11:3 5|67:3 6|46:3 7|9:4 1|59:4 2|9:4 3|19:4 4|44:4 5|22:4 6|7:4 7|82:5 1|11:5 2|34:5 3|96:5 4|19:5 5|17:5 6|75:5 7|36:6 1|65:6 2|24:6 3|74:6 4|79:6 5|27:6 6|21:6 7|83:7 1|41:7 2|68:7 3|38:7 4|68:7 5|27:7 6|21:7 7</relation>
    <relation name="R22" arity="2" nbTuples="49" semantics="soft" defaultCost="infinity">16:1 1|43:1 2|22:1 3|89:1 4|21:1 5|37:1 6|77:1 7|90:2 1|98:2 2|57:2 3|92:2 4|12:2 5|16:2 6|2:2 7|31:3 1|31:3 2|84:3 3|68:3 4|95:3 5|97:3 6|64:3 7|23:4 1|65:4 2|34:4 3|73:4 4|31:4 5|7:4 6|32:4 7|91:5 1|24:5 2|43:5 3|44:5 4|57:5 5|34:5 6|19:5 7|75:6 1|2:6 2|48:6 3|37:6 4|83:6 5|7:6 6|21:6 7|99:7 1|44:7 2|68:7 3|0:7 4|88:7 5|63:7 6|65:7 7</relation>
    <relation name="R23" arity="2" nbTuples="49" semantics="soft" defaultCost="infinity">13:1 1|8:1 2|39:1 3|81:1 4|89:1 5|60:1 6|46:1 7|98:2 1|7:2 2|28:2 3|19:2 4|47:2 5|47:2 6|78:2 7|89:3 1|28:3 2|98:3 3|77:3 4|38:3 5|13:3 6|13:3 7|44:4 1|20:4 2|21:4 3|70:4 4|55:4 5|45:4 6|57:4 7|11:5 1|72:5 2|27:5 3|81:5 4|46:5 5|65:5 6|81:5 7|85:6 1|30:6 2|96:6 3|23:6 4|29:6 5|78:6 6|51:6 7|37:7 1|28:7 2|16:7 3|28:7 4|67:7 5|34:7 6|24:7 7</relation>
    <relation name="R24" arity="2" nbTuples="49" semantics="soft" defaultCost="infinity">82:1 1|55:1 2|18:1 3|31:1 4|89:1 5|20:1 6|17:1 7|70:2 1|75:2 2|73:2 3|76:2 4|16:2 5|15:2 6|77:2 7|69:3 1|50:3 2|13:3 3|72:3 4|73:3 5|81:3 6|28:3 7|3:4 1|34:4 2|97:4 3|30:4 4|62:4 5|21:4 6|15:4 7|29:5 1|69:5 2|72:5 3|32:5 4|43:5 5|99:5 6|10:5 7|77:6 1|31:6 2|57:6 3|72:6 4|56:6 5|65:6 6|44:6 7|8:7 1|4:7 2|61:7 3|86:7 4|97:7 5|21:7 6|41:7 7</relation>
    <relation name="R25" arity="2" nbTuples="49" semantics="soft" defaultCost="infinity">10:1 1|79:1 2|67:1 3|89:1 4|75:1 5|92:1 6|80:1 7|62:2 1|27:2 2|82:2 3|52:2 4|63:2 5|50:2 6|67:2 7|45:3 1|72:3 2|40:3 3|78:3 4|37:3 5|62:3 6|61:3 7|39:4 1|20:4 2|70:4 3|38:4 4|41:4 5|14:4 6|83:4 7|45:5 1|7:5 2|61:5 3|62:5 4|44:5 5|40:5 6|51:5 7|48:6 1|88:6 2|87:6 3|94:6 4|27:6 5|34:6 6|63:6 7|8:7 1|82:7 2|47:7 3|21:7 4|95:7 5|91:7 6|62:7 7</relation>
    <relation name="R26" arity="2" nbTuples="49" semantics="soft" defaultCost="infinity">85:1 1|66:1 2|84:1 3|36:1 4|67:1 5|12:1 6|27:1 7|12:2 1|3:2 2|94:2 3|25:2 4|95:2 5|87:2 6|89:2 7|38:3 1|100:3 2|96:3 3|97:3 4|19:3 5|88:3 6|36:3 7|83:4 1|70:4 2|85:4 3|62:4 4|18:4 5|62:4 6|13:4 7|2:5 1|46:5 2|62:5 3|98:5 4|74:5 5|61:5 6|26:5 7|6:6 1|28:6 2|83:6 3|60:6 4|55:6 5|32:6 6|83:6 7|67:7 1|69:7 2|54:7 3|80:7 4|23:7 5|34:7 6|4:7 7</relation>
    <relation name="R27" arity="2" nbTuples="49" semantics="soft" defaultCost="infinity">65:1 1|79:1 2|68:1 3|37:1 4|13:1 5|96:1 6|47:1 7|3:2 1|61:2 2|84:2 3|83:2 4|37:2 5|54:2 6|46:2 7|0:3 1|6:3 2|76:3 3|73:3 4|83:3 5|87:3 6|32:3 7|90:4 1|55:4 2|61:4 3|33:4 4|16:4 5|74:4 6|81:4 7|36:5 1|29:5 2|19:5 3|95:5 4|31:5 5|11:5 6|57:5 7|40:6 1|46:6 2|98:6 3|33:6 4|33:6 5|90:6 6|34:6 7|61:7 1|49:7 2|38:7 3|84:7 4|34:7 5|18:7 6|43:7 7</relation>
    <relation name="R28" arity="2" nbTuples="49" semantics="soft" defaultCost="infinity">27:1 1|60:1 2|81:1 3|2:1 4|71:1 5|3:1 6|34:1 7|38:2 1|22:2 2|91:2 3|32:2 4|70:2 5|25:2 6|41:2 7|26:3 1|28:3 2|83:3 3|21:3 4|47:3 5|30:3 6|8:3 7|16:4 1|54:4 2|81:4 3|36:4 4|34:4 5|12:4 6|84:4 7|99:5 1|91:5 2|98:5 3|37:5 4|95:5 5|36:5 6|33:5 7|82:6 1|53:6 2|13:6 3|46:6 4|99:6 5|15:6 6|100:6 7|33:7 1|24:7 2|50:7 3|30:7 4|97:7 5|14:7 6|39:7 7</relation>
    <relation name="R29" arity="2" nbTuples="49" semantics="soft" defaultCost="infinity">0:1 1|37:1 2|25:1 3|71:1 4|60:1 5|67:1 6|5:1 7|98:2 1|12:2 2|29:2 3|73:2 4|32:2 5|27:2 6|1:2 7|50:3 1|91:3 2|56:3 3|90:3 4|37:3 5|75:3 6|67:3 7|4:4 1|7:4 2|79:4 3|27:4 4|64:4 5|6:4 6|61:4 7|17:5 1|53:5 2|66:5 3|26:5 4|63:5 5|13:5 6|48:5 7|42:6 1|84:6 2|58:6 3|30:6 4|94:6 5|90:6 6|35:6 7|34:7 1|100:7 2|40:7 3|80:7 4|96:7 5|77:7 6|82:7 7</relation>
  </relations>
  <GuiPresentation type="DCOP" benchmark="RandomDCOP" name="instance24" model="TKC" nbAgents="18" domainSize="7" density="0" tightness="0" nbConstraints="30" nbTuples="49" />
</instance>